spindle/__init__.py
spindle/main.py
spindle_merge-1.0.2.dist-info/LICENCE
spindle_merge-1.0.2.dist-info/METADATA
spindle_merge-1.0.2.dist-info/WHEEL
spindle_merge-1.0.2.dist-info/entry_points.txt
spindle_merge-1.0.2.dist-info/top_level.txt
spindle_merge-1.0.2.dist-info/RECORD
