Metadata-Version: 2.1
Name: spindle-merge
Version: 1.0.2
Summary: A command-line tool for merging files with wildcard support.
Home-page: https://github.com/ll3ynxnj/spindle
Author: ll3Ynxnj
Author-email: ll3ynxnj@claywork.co.jp
Classifier: Programming Language :: Python :: 3
Classifier: License :: OSI Approved :: MIT License
Classifier: Operating System :: OS Independent
Requires-Python: >=3.6
License-File: LICENCE
